fate_testsuite/__init__.py
fate_testsuite/_ascii.py
fate_testsuite/_client.py
fate_testsuite/_config.py
fate_testsuite/_flow_client.py
fate_testsuite/_io.py
fate_testsuite/_parser.py
fate_testsuite/cli.py
sage_testsuite-0.1.0a6.dist-info/entry_points.txt
sage_testsuite-0.1.0a6.dist-info/WHEEL
sage_testsuite-0.1.0a6.dist-info/METADATA
sage_testsuite-0.1.0a6.dist-info/RECORD
